slapp_py/__init__.py
slapp_py/core_classes/__init__.py
slapp_py/core_classes/battlefy.py
slapp_py/core_classes/bracket.py
slapp_py/core_classes/builtins.py
slapp_py/core_classes/clan_tag.py
slapp_py/core_classes/discord.py
slapp_py/core_classes/division.py
slapp_py/core_classes/divisions_handler.py
slapp_py/core_classes/friend_code.py
slapp_py/core_classes/friend_code_handler.py
slapp_py/core_classes/game.py
slapp_py/core_classes/name.py
slapp_py/core_classes/placement.py
slapp_py/core_classes/player.py
slapp_py/core_classes/pronoun.py
slapp_py/core_classes/pronoun_flags.py
slapp_py/core_classes/score.py
slapp_py/core_classes/simple_source.py
slapp_py/core_classes/skill.py
slapp_py/core_classes/source.py
slapp_py/core_classes/tag_option.py
slapp_py/core_classes/team.py
slapp_py/core_classes/teams_handler.py
slapp_py/core_classes/socials/__init__.py
slapp_py/core_classes/socials/battlefy_team_social.py
slapp_py/core_classes/socials/battlefy_user_social.py
slapp_py/core_classes/socials/plus_membership.py
slapp_py/core_classes/socials/sendou.py
slapp_py/core_classes/socials/social.py
slapp_py/core_classes/socials/twitch.py
slapp_py/core_classes/socials/twitter.py
slapp_py/helpers/__init__.py
slapp_py/helpers/battlefy_helper.py
slapp_py/helpers/console_helper.py
slapp_py/helpers/dict_helper.py
slapp_py/helpers/fetch_helper.py
slapp_py/helpers/str_helper.py
slapp_py/misc/__init__.py
slapp_py/misc/consts.py
slapp_py/misc/create_tables.py
slapp_py/misc/download_from_battlefy_result.py
slapp_py/misc/download_from_challonge.py
slapp_py/misc/download_from_sendou.py
slapp_py/misc/download_from_smashgg.py
slapp_py/misc/download_from_statink.py
slapp_py/misc/download_from_toonament.py
slapp_py/misc/new_sources_file.py
slapp_py/misc/organise_local.py
slapp_py/misc/slapp_files_utils.py
slapp_py/misc/transfer_to_postgres.py
slapp_py/misc/transform_sendou_file.py
slapp_py/misc/models/__init__.py
slapp_py/misc/models/battlefy_player.py
slapp_py/misc/models/battlefy_team.py
SlappPy_Slate-1.14.7.dist-info/LICENSE
SlappPy_Slate-1.14.7.dist-info/METADATA
SlappPy_Slate-1.14.7.dist-info/WHEEL
SlappPy_Slate-1.14.7.dist-info/top_level.txt
SlappPy_Slate-1.14.7.dist-info/RECORD
