Metadata-Version: 2.1
Name: SlappPy-Slate
Version: 1.14.7
Summary: SlappPy is the Python support and generation code for Slapp and Dola.
Home-page: https://github.com/kjhf/SlappPy
Author: Slate
License: UNKNOWN
Project-URL: Bug Reports, https://github.com/kjhf/SlappPy/issues
Project-URL: Source, https://github.com/kjhf/SlappPy/
Project-URL: Discord, https://discord.gg/wZZv2Cr
Keywords: slapp,slate,splatoon
Platform: UNKNOWN
Classifier: Development Status :: 3 - Alpha
Classifier: Intended Audience :: Developers
Classifier: Topic :: Software Development :: Build Tools
Classifier: Programming Language :: Python :: 3.9
Classifier: License :: OSI Approved :: MIT License
Classifier: Operating System :: OS Independent
Requires-Python: >=3.9, <4
License-File: LICENSE
